Metadata-Version: 2.1
Name: py-GBdistribution
Version: 1.5
Summary: Gaussian and Binomial distributions package
Home-page: UNKNOWN
License: UNKNOWN
Platform: UNKNOWN
